README.rst
multitail
multitail.py
setup.py
multitail_curses.egg-info/PKG-INFO
multitail_curses.egg-info/SOURCES.txt
multitail_curses.egg-info/dependency_links.txt
multitail_curses.egg-info/top_level.txt