Metadata-Version: 1.1
Name: multitail-curses
Version: 1.0.5
Summary: A curses-based utility script for tailing multiple files simultaneously.
Home-page: http://github.com/thobbs/multitail-curses
Author: Tyler Hobbs
Author-email: tylerlhobbs@gmail.com
License: MIT
Download-URL: http://github.com/thobbs/multitail-curses/archive/1.0.5.tar.gz
Keywords: tail script multitail
Platform: UNKNOWN
Classifier: Development Status :: 5 - Production/Stable
Classifier: Topic :: Utilities
Classifier: License :: OSI Approved :: MIT License
Classifier: Natural Language :: English
Classifier: Operating System :: OS Independent
Classifier: Programming Language :: Python
Classifier: Programming Language :: Python :: 2
Classifier: Programming Language :: Python :: 2.6
Classifier: Programming Language :: Python :: 2.7
Classifier: Programming Language :: Python :: 2 :: Only
